trackball/__init__.py
trackball-0.0.1.dist-info/DESCRIPTION.rst
trackball-0.0.1.dist-info/METADATA
trackball-0.0.1.dist-info/RECORD
trackball-0.0.1.dist-info/WHEEL
trackball-0.0.1.dist-info/metadata.json
trackball-0.0.1.dist-info/top_level.txt
